lunexa_api/__init__.py
lunexa_api/api.py
lunexa/__init__.py
lunexa/cli.py
lunexa/core/__init__.py
lunexa/core/utils.py
lunexa_core-0.1.0.dist-info/LICENSE
lunexa_core-0.1.0.dist-info/METADATA
lunexa_core-0.1.0.dist-info/WHEEL
lunexa_core-0.1.0.dist-info/entry_points.txt
lunexa_core-0.1.0.dist-info/RECORD
