Metadata-Version: 2.3
Name: lunexa-core
Version: 0.1.0
Summary: Umbrella CLI & shared utils for all Lunexa projects
License: MIT
Author: Simbarashe Timire
Author-email: stimire92@gmail.com
Requires-Python: >=3.9,<3.13
Classifier: License :: OSI Approved :: MIT License
Classifier: Programming Language :: Python :: 3
Classifier: Programming Language :: Python :: 3.9
Classifier: Programming Language :: Python :: 3.10
Classifier: Programming Language :: Python :: 3.11
Classifier: Programming Language :: Python :: 3.12
Requires-Dist: fastapi (>=0.116.1,<0.117.0)
Requires-Dist: pydantic-settings (>=2.1,<3.0)
Requires-Dist: rich (>=13.7,<14.0)
Requires-Dist: typer[all] (>=0.12.3,<0.13.0)
Requires-Dist: uvicorn[standard] (>=0.35.0,<0.36.0)
